catalog/__init__.py
catalog/main.py
catalog/forms/__init__.py
catalog/forms/app.py
catalog/forms/ingredients.py
catalog/forms/recipes.py
catalog/storage/__init__.py
catalog/storage/sqlite.py
catalog/storage/sqlite.schema
ghostdev.recipe_catalog-1.0.2.dist-info/METADATA
ghostdev.recipe_catalog-1.0.2.dist-info/WHEEL
ghostdev.recipe_catalog-1.0.2.dist-info/top_level.txt
ghostdev.recipe_catalog-1.0.2.dist-info/RECORD
